agora/__init__.py
agora/_asset.py
agora/_base_client.py
agora/_client.py
agora/_exceptions.py
agora/_models.py
agora/_paths.py
agora/_resource.py
agora/cli/__init__.py
agora/resources/library.py
agora/resources/management.py
agora/resources/market.py
agora_sdk-1.0.0a3.dist-info/METADATA
agora_sdk-1.0.0a3.dist-info/WHEEL
agora_sdk-1.0.0a3.dist-info/licenses/LICENSE
agora_sdk-1.0.0a3.dist-info/RECORD
