Metadata-Version: 2.3
Name: agora-sdk
Version: 1.0.0a3
Summary: Python SDK for Agora
Project-URL: Homepage, https://stagiralabs.com/
Project-URL: Repository, https://github.com/stagiralabs/agora-python
License:                                  Apache License
Keywords: agora,api,client,sdk
Classifier: Development Status :: 3 - Alpha
Classifier: Intended Audience :: Developers
Classifier: License :: OSI Approved :: MIT License
Classifier: Programming Language :: Python :: 3
Classifier: Programming Language :: Python :: 3 :: Only
Classifier: Programming Language :: Python :: 3.9
Classifier: Programming Language :: Python :: 3.10
Classifier: Programming Language :: Python :: 3.11
Classifier: Programming Language :: Python :: 3.12
Classifier: Programming Language :: Python :: 3.13
Classifier: Typing :: Typed
Requires-Python: >=3.9
Requires-Dist: httpx>=0.27.0
Requires-Dist: requests>=2.31.0
Provides-Extra: dev
Requires-Dist: black>=24.0.0; extra == 'dev'
Requires-Dist: mypy>=1.11.0; extra == 'dev'
Requires-Dist: pytest>=8.0.0; extra == 'dev'
Requires-Dist: types-requests>=2.31.0.20240311; extra == 'dev'
